errzip/__init__.py
errzip-0.1.0.dist-info/licenses/LICENSE
errzip-0.1.0.dist-info/METADATA
errzip-0.1.0.dist-info/WHEEL
errzip-0.1.0.dist-info/top_level.txt
errzip-0.1.0.dist-info/RECORD
