Metadata-Version: 2.4
Name: errzip
Version: 0.1.0
Summary: AI-optimized exception summarization that automatically sends to LLMs
Home-page: https://github.com/yourusername/errzip
Author: Your Name
Author-email: Greg <greg@example.com>
Maintainer-email: Greg <greg@example.com>
License: MIT
Project-URL: Homepage, https://github.com/yourusername/errzip
Project-URL: Documentation, https://github.com/yourusername/errzip#readme
Project-URL: Repository, https://github.com/yourusername/errzip.git
Project-URL: Issues, https://github.com/yourusername/errzip/issues
Project-URL: Changelog, https://github.com/yourusername/errzip/blob/main/CHANGELOG.md
Keywords: exception,error,debugging,ai,llm,ollama,openai,claude,diagnostics,traceback
Classifier: Development Status :: 3 - Alpha
Classifier: Intended Audience :: Developers
Classifier: Topic :: Software Development :: Debuggers
Classifier: Topic :: Software Development :: Quality Assurance
Classifier: Topic :: System :: Monitoring
Classifier: License :: OSI Approved :: MIT License
Classifier: Programming Language :: Python :: 3
Classifier: Programming Language :: Python :: 3.8
Classifier: Programming Language :: Python :: 3.9
Classifier: Programming Language :: Python :: 3.10
Classifier: Programming Language :: Python :: 3.11
Classifier: Programming Language :: Python :: 3.12
Classifier: Programming Language :: Python :: 3.13
Classifier: Operating System :: OS Independent
Requires-Python: >=3.8
License-File: LICENSE
Requires-Dist: requests>=2.25.0
Provides-Extra: dev
Requires-Dist: pytest>=7.0.0; extra == "dev"
Requires-Dist: black>=22.0.0; extra == "dev"
Requires-Dist: mypy>=0.990; extra == "dev"
Requires-Dist: flake8>=6.0.0; extra == "dev"
Dynamic: author
Dynamic: home-page
Dynamic: license-file
Dynamic: requires-python
